{
  "summary": {
    "PaddleOCR": {
      "texts": 279,
      "time_ms": 1391260.369334,
      "images_with_text": 21,
      "unique": 237,
      "errors": 0
    },
    "EasyOCR": {
      "texts": 132,
      "time_ms": 167689.96799999988,
      "images_with_text": 13,
      "unique": 88,
      "errors": 0
    },
    "docTR": {
      "texts": 117,
      "time_ms": 30938.795457000313,
      "images_with_text": 15,
      "unique": 71,
      "errors": 0
    }
  },
  "results": [
    {
      "image": "16195360_1469198399779947_1598506099658570170_n.jpg",
      "engines": {
        "PaddleOCR": {
          "texts": [
            [
              "TWO NATIONALLY KNOWN",
              0.9985138773918152
            ],
            [
              "BROADCASTING BANDS COMING",
              0.9873327612876892
            ],
            [
              "TO THE",
              0.9873635768890381
            ],
            [
              "COLISEUM - - Ceres, N. Y.",
              0.9566951990127563
            ],
            [
              "SATURDAY EVENING, MAY 7th",
              0.9972936511039734
            ],
            [
              "9P.M.",
              0.9968112707138062
            ],
            [
              "PARK PLAN",
              0.9992444515228271
            ],
            [
              "BOBBIE GRICE and Her 14 Bricktops",
              0.9890024662017822
            ],
            [
              "ALL REDHEADS -ALL STARS -VITA-",
              0.9760962724685669
            ],
            [
              "PHONE ARTISTS-VAUDEVILLE HEAD.",
              0.9773709177970886
            ],
            [
              "LINERS -FOX, LOEW. RKO. RADIO",
              0.9728207588195801
            ],
            [
              "FAVORITESNONE BETTER! The best",
              0.969721257686615
            ],
            [
              "girls' orchestra in Arnerica!",
              0.9926242232322693
            ],
            [
              "WEDNESDAY EVENING, MAY IIth",
              0.9669833183288574
            ],
            [
              "9P.M.",
              0.9962665438652039
            ],
            [
              "PARK PLAN",
              0.9993952512741089
            ],
            [
              "TAL HENRY & His North Carolinians",
              0.9807567000389099
            ],
            [
              "EXCLUSIVE VICTOR ARTISTS DIRECT",
              0.9849292039871216
            ],
            [
              "FROM HOTEL NEW YORKER",
              0.9972363710403442
            ],
            [
              "Two of this country's best dance orchestras, in",
              0.9889070391654968
            ],
            [
              "Southwestern New York's Finest Ballroom -",
              0.9690525531768799
            ],
            [
              "Don't Miss These Super Attractions!",
              0.9808223247528076
            ]
          ],
          "time_ms": 6260.2,
          "error": null
        },
        "EasyOCR": {
          "texts": [
            [
              "TWO NATIONALLY KNOWN",
              0.8779434650871202
            ],
            [
              "BROADCASTING BANDS COMINC",
              0.9108983828942507
            ],
            [
              "TO",
              0.961514438364817
            ],
            [
              "THE",
              0.9826088471766705
            ],
            [
              "COLISEUM_",
              0.9944345532282296
            ],
            [
              "Ceres, N Y:",
              0.6156987687729484
            ],
            [
              "SATURDAY EVENING_",
              0.9985135632739676
            ],
            [
              "MAY Tth",
              0.8767389028755151
            ],
            [
              "9 P",
              0.9671782321122819
            ],
            [
              "PARK PLAN",
              0.8596462450507172
            ],
            [
              "BOBBIE GRICE and Her i4 Bricktops",
              0.6577576075932704
            ],
            [
              "ALL REDHEADS",
              0.9526999995795352
            ],
            [
              "ALL STARS",
              0.9978551196796474
            ],
            [
              "VTA-",
              0.5555058717727661
            ],
            [
              "PHONE ARTISTS",
              0.6412030455220468
            ],
            [
              "VAUDEVILLK HEAD",
              0.5992429033788598
            ],
            [
              "LINERS",
              0.9998529259294537
            ],
            [
              "FOX",
              0.5469171339341775
            ],
            [
              "LOEW",
              0.6026350259780884
            ],
            [
              "RKO.",
              0.9940549731254578
            ],
            [
              "RADIO",
              0.9941668802124697
            ],
            [
              "FAVORITES",
              0.9996736180688998
            ],
            [
              "NONE",
              0.9962577223777771
            ],
            [
              "BETTER!",
              0.9660488262233747
            ],
            [
              "The:",
              0.37608739733695984
            ],
            [
              "bcst",
              0.9012247920036316
            ],
            [
              "girls' orchestra in Arnerica !",
              0.5533484744320517
            ],
            [
              "WEDNESDAY EVENING,",
              0.8006899430385742
            ],
            [
              "MAY Ith",
              0.4066468181966914
            ],
            [
              "9 P.",
              0.7157191038131714
            ],
            [
              "PARK PLAN",
              0.87366944898185
            ],
            [
              "TAL HENRY & His North Carolinians",
              0.9150016852255363
            ],
            [
              "EXCLUSIVE",
              0.990417894247669
            ],
            [
              "VICTOR ARTISTS",
              0.7153023878212136
            ],
            [
              "DJRECT",
              0.8171466613162642
            ],
            [
              "FROM HOTEL NEW YORKER",
              0.8077867884986458
            ],
            [
              "Two of this colhtry' # bcst dlance orchcstras_",
              0.34580440938929274
            ],
            [
              "Southwestern New Yorks Fincst Ballrcom",
              0.7996219601095957
            ]
          ],
          "time_ms": 1103.2,
          "error": null
        },
        "docTR": {
          "texts": [
            [
              "TwO NATIONALLY KNOWN",
              0.8971392711003622
            ],
            [
              "BROADCASTING BANDS COMING",
              0.887152353922526
            ],
            [
              "1o THE",
              0.48388347029685974
            ],
            [
              "COLISEUM",
              0.908280074596405
            ],
            [
              "- - Ceres,",
              0.8825644056002299
            ],
            [
              "N. - Y.",
              0.7864743570486704
            ],
            [
              "SATURDAY EVENING, MAY 7th",
              0.9033374190330505
            ],
            [
              "9P.M.",
              0.8125715851783752
            ],
            [
              "PARK PLAN",
              0.9376474022865295
            ],
            [
              "BUBBIE GRICE and Her 14 Bricktops",
              0.886415476600329
            ],
            [
              "ALL REDHEADS",
              0.9905154705047607
            ],
            [
              "- ALL STARS",
              0.8068758050600687
            ],
            [
              "VITA-",
              0.9881216287612915
            ],
            [
              "PHONE ARTISTS-VAUDEVILLE HEAD-",
              0.7760088443756104
            ],
            [
              "LINERS",
              0.7081044316291809
            ],
            [
              "roX,",
              0.5043373107910156
            ],
            [
              "LOEW, RKO.",
              0.8402349352836609
            ],
            [
              "RAJIO",
              0.830969512462616
            ],
            [
              "FAVORITES --NONE BETTER!",
              0.813400387763977
            ],
            [
              "The bcst",
              0.7655170857906342
            ],
            [
              "girls' orchestra in Arnerica!",
              0.8331677988171577
            ],
            [
              "WEDNESDAY EVENING, MAY lth",
              0.8983883261680603
            ],
            [
              "9P. M.",
              0.9171959757804871
            ],
            [
              "PARK PLAN",
              0.9957257211208344
            ],
            [
              "TAL HENRY & His North Carolinians",
              0.9452574054400126
            ],
            [
              "EXCLUSIVE VICTOR ARTISTS DIRECT",
              0.9170122593641281
            ],
            [
              "FROM HOTEL NEW YORKEK",
              0.7877116054296494
            ],
            [
              "Two of this country's best dance orchestras, 101",
              0.8009082525968552
            ],
            [
              "Southwestern New York's Finest Ballroom",
              0.9690659880638123
            ],
            [
              "Don't Miss These Super Attractions!",
              0.904112708568573
            ]
          ],
          "time_ms": 4044.8,
          "error": null
        }
      }
    },
    {
      "image": "5c80a25be26b6.image.jpeg",
      "engines": {
        "PaddleOCR": {
          "texts": [
            [
              "CERES POWER HOUSE",
              0.9963687658309937
            ],
            [
              "SNOW TWIN TANDEM",
              0.9993237257003784
            ],
            [
              "500 BHP GAS ENGINE",
              0.9807438254356384
            ],
            [
              "1906",
              0.9996886253356934
            ]
          ],
          "time_ms": 2208.8,
          "error": null
        },
        "EasyOCR": {
          "texts": [
            [
              "CERES POWER HOUSE",
              0.9767199808658915
            ],
            [
              "SNOW TWIN TANDEM",
              0.9982978818698818
            ],
            [
              "500 BHP GAS ENGINE",
              0.8155057671685128
            ],
            [
              "1906",
              0.9999805688858032
            ]
          ],
          "time_ms": 507.2,
          "error": null
        },
        "docTR": {
          "texts": [
            [
              "CERES POWER HOUSE",
              0.996526300907135
            ],
            [
              "SNOW TWIN TANDEM",
              0.9811320702234904
            ],
            [
              "500 BHP GAS ENGINE",
              0.9990528672933578
            ],
            [
              "S",
              0.6361299753189087
            ],
            [
              "1906",
              0.9987791180610657
            ]
          ],
          "time_ms": 715.1,
          "error": null
        }
      }
    },
    {
      "image": "5c80a6e942b29.image.jpeg",
      "engines": {
        "PaddleOCR": {
          "texts": [
            [
              "ard",
              0.7060599327087402
            ],
            [
              "Opening",
              0.9992582201957703
            ],
            [
              "The",
              0.9946451783180237
            ],
            [
              "Coliseum",
              0.9368773698806763
            ],
            [
              "Thanksgiving",
              0.9384713172912598
            ],
            [
              "Night,",
              0.9730264544487
            ],
            [
              "Nov. 26",
              0.9900916814804077
            ],
            [
              "Allegany",
              0.9729679822921753
            ],
            [
              "County's Newest and Finest Ball Room",
              0.9730438590049744
            ],
            [
              "Route",
              0.9943619966506958
            ],
            [
              "17-6",
              0.9979386329650879
            ],
            [
              "miles",
              0.9997919201850891
            ],
            [
              "south",
              0.9999162554740906
            ],
            [
              "of Bolivar",
              0.9981487393379211
            ],
            [
              "12",
              0.9999186992645264
            ],
            [
              "miles north",
              0.9972971081733704
            ],
            [
              "of",
              0.9992548823356628
            ],
            [
              "Olean",
              0.9996787905693054
            ],
            [
              "Dancing-Park Plan-9 p.m. to 1 a.m.",
              0.9747166633605957
            ],
            [
              "The Best Broadcasting",
              0.9977933764457703
            ],
            [
              "Orchestra",
              0.9997348785400391
            ],
            [
              "Will Furnish Music",
              0.9810532331466675
            ],
            [
              "Everything new and up to-date.",
              0.9802344441413879
            ],
            [
              "The latest lighting",
              0.9514892101287842
            ],
            [
              "cffects.",
              0.9754073619842529
            ],
            [
              "Plenty of parking space.",
              0.970280647277832
            ],
            [
              "Dance floor 7,000",
              0.9400213360786438
            ],
            [
              "square feet.",
              0.9879950881004333
            ],
            [
              "Steam heat.",
              0.9854502081871033
            ],
            [
              "Lunch",
              0.9989867210388184
            ],
            [
              "room in connection",
              0.9850441813468933
            ],
            [
              "You've Seen the Others-Now Visit the Coliseum",
              0.9904547929763794
            ]
          ],
          "time_ms": 5195.6,
          "error": null
        },
        "EasyOCR": {
          "texts": [
            [
              "Gala Opening",
              0.5972723478749906
            ],
            [
              "Gbe",
              0.9268368838446882
            ],
            [
              "Coliseum",
              0.9999166742424905
            ],
            [
              "Allegany County $ Newest and Finest Ball Room",
              0.7185275386958061
            ],
            [
              "12 miles north of Olean",
              0.31726915744642353
            ],
            [
              "Dancing-Park Plan-9pm to 1am",
              0.7434062590762094
            ],
            [
              "The Best Broadcasting Orchestra",
              0.9645198440078265
            ],
            [
              "Will Furnish Mlusic",
              0.7586319052425252
            ],
            [
              "cifects:",
              0.5822023979596682
            ],
            [
              "Plenty of parking",
              0.5658474520853678
            ],
            [
              "room In connectlon-",
              0.40988630793429537
            ],
            [
              "You've Seen the Others-Now Visit the Coliseum",
              0.6752943677648537
            ]
          ],
          "time_ms": 844.7,
          "error": null
        },
        "docTR": {
          "texts": [
            [
              "- Gala Opening",
              0.8393747210502625
            ],
            [
              "Gihbe",
              0.3826676905155182
            ],
            [
              "Coliseum",
              0.954725980758667
            ],
            [
              "Ihanksgiving",
              0.44883593916893005
            ],
            [
              "Nigut Nov. 26",
              0.8125943144162496
            ],
            [
              "Allegany County's Newest and finest Ball Room",
              0.8780920037201473
            ],
            [
              "Boute 17-6 milles south of Bolivar",
              0.7347769637902578
            ],
            [
              "12 miles north of Olean",
              0.8701061129570007
            ],
            [
              "Dancing-Park Plan-9 p.m.tol a.m.",
              0.7704514265060425
            ],
            [
              "The Best Broadcasting Orchestra",
              0.990853875875473
            ],
            [
              "Will Furnish Music",
              0.7251062591870626
            ],
            [
              "Everything new and upto-date.",
              0.8408896923065186
            ],
            [
              "The latest lighting",
              0.9319882988929749
            ],
            [
              "cffects.",
              0.9142910838127136
            ],
            [
              "Plenty of parking Epace.",
              0.9593777805566788
            ],
            [
              "Dance floor 7,000",
              0.8554736773173014
            ],
            [
              "square feet.",
              0.8100970685482025
            ],
            [
              "Steam heat,",
              0.6272570788860321
            ],
            [
              "Lunch room in connection.",
              0.9780898988246918
            ],
            [
              "You've Seen the Others-Now Visit the Coliseum",
              0.8672412208148411
            ],
            [
              "Every Dance A Hit - -",
              0.8846643368403116
            ]
          ],
          "time_ms": 3333.0,
          "error": null
        }
      }
    },
    {
      "image": "Bus Mechanic House (2).jpg",
      "engines": {
        "PaddleOCR": {
          "texts": [
            [
              "07088",
              0.5782619118690491
            ],
            [
              "NE VENTURE",
              0.9767225384712219
            ],
            [
              "SPEEDWAY",
              0.957950234413147
            ],
            [
              "5 W ANON NEW YORK",
              0.7663141489028931
            ],
            [
              "(315)829-2777",
              0.9897403120994568
            ],
            [
              "Eny   o",
              0.4691835343837738
            ],
            [
              "Cwop",
              0.44597166776657104
            ],
            [
              "NOA",
              0.3969604969024658
            ],
            [
              "LOA",
              0.4623061716556549
            ],
            [
              "IRON",
              0.9949120879173279
            ],
            [
              "PERCE&SIEA",
              0.6836000084877014
            ],
            [
              "ON",
              0.9495405554771423
            ],
            [
              "1/25 SEALE REWORTH",
              0.7728221416473389
            ],
            [
              "X-TRACTOR",
              0.8970187306404114
            ],
            [
              "KDA",
              0.32231882214546204
            ],
            [
              "NA",
              0.4280990958213806
            ],
            [
              "KAR PRODUCTS",
              0.9993036389350891
            ],
            [
              "N",
              0.3487465977668762
            ],
            [
              "17",
              0.45392099022865295
            ]
          ],
          "time_ms": 134640.4,
          "error": null
        },
        "EasyOCR": {
          "texts": [
            [
              "VentuRE",
              0.5258686718474448
            ],
            [
              "I",
              0.7993645212471598
            ],
            [
              "KaR",
              0.37380649027053037
            ],
            [
              "PRODUCTS",
              0.5777885344851621
            ]
          ],
          "time_ms": 8529.2,
          "error": null
        },
        "docTR": {
          "texts": [],
          "time_ms": 862.0,
          "error": null
        }
      }
    },
    {
      "image": "Bus Mechanic House (23).jpg",
      "engines": {
        "PaddleOCR": {
          "texts": [
            [
              "amnZA",
              0.40337568521499634
            ],
            [
              "<>3",
              0.8778395652770996
            ],
            [
              "DD3",
              0.777394711971283
            ],
            [
              "DU>",
              0.6396088004112244
            ],
            [
              "NEW YORK",
              0.9923071265220642
            ],
            [
              "SEE AE E E",
              0.4413403570652008
            ],
            [
              "OWMOBILE REGISTRATION",
              0.9906193614006042
            ],
            [
              "<OZ",
              0.909075915813446
            ],
            [
              "-0O",
              0.3265404999256134
            ],
            [
              "OmO",
              0.74899822473526
            ]
          ],
          "time_ms": 65729.3,
          "error": null
        },
        "EasyOCR": {
          "texts": [
            [
              "8",
              0.5095628764211177
            ],
            [
              "0F",
              0.5326634872384994
            ],
            [
              "8",
              0.7419236169738816
            ],
            [
              "044u",
              0.4930717945098877
            ],
            [
              "NEW",
              0.873586023695739
            ],
            [
              "YorK",
              0.5133756399154663
            ],
            [
              "REGISTAATION",
              0.4927743249560275
            ],
            [
              "Vehicles",
              0.34410529416753666
            ],
            [
              "2",
              0.5972652101093878
            ]
          ],
          "time_ms": 9137.9,
          "error": null
        },
        "docTR": {
          "texts": [
            [
              "NEW",
              0.7476868033409119
            ],
            [
              "YORK",
              0.7241872549057007
            ],
            [
              "ILE",
              0.9959789514541626
            ],
            [
              "844U",
              0.48059317469596863
            ],
            [
              "REGIS STRATION",
              0.7598688900470734
            ],
            [
              "*",
              0.3449111580848694
            ]
          ],
          "time_ms": 1092.3,
          "error": null
        }
      }
    },
    {
      "image": "Bus Mechanic House (5).jpg",
      "engines": {
        "PaddleOCR": {
          "texts": [
            [
              "D",
              0.32149532437324524
            ],
            [
              "4",
              0.4567948877811432
            ],
            [
              "Size",
              0.9760227799415588
            ],
            [
              "Supe",
              0.8587883710861206
            ],
            [
              "Lock's Stock & Barrel",
              0.9636469483375549
            ],
            [
              "GREAT FOOD. . GREAT MUSIC",
              0.8915384411811829
            ],
            [
              "JUNIOR'S",
              0.9036851525306702
            ],
            [
              "FeB 20  BRIAN AVERS & BE",
              0.802828311920166
            ],
            [
              "ELIXIR",
              0.8805639147758484
            ]
          ],
          "time_ms": 73891.3,
          "error": null
        },
        "EasyOCR": {
          "texts": [
            [
              "1",
              0.7348163081586314
            ]
          ],
          "time_ms": 9625.9,
          "error": null
        },
        "docTR": {
          "texts": [],
          "time_ms": 1179.7,
          "error": null
        }
      }
    },
    {
      "image": "Bus Mechanic House (6).jpg",
      "engines": {
        "PaddleOCR": {
          "texts": [
            [
              "C",
              0.4734894335269928
            ],
            [
              "TR",
              0.46392685174942017
            ],
            [
              "eise",
              0.598239541053772
            ],
            [
              "DAYTONA",
              0.9996196627616882
            ],
            [
              "BEACH",
              0.9996312856674194
            ],
            [
              "SPEEDWAY",
              0.9186903238296509
            ],
            [
              "Internationai",
              0.9692555069923401
            ],
            [
              "Fla.",
              0.9747775793075562
            ],
            [
              "C",
              0.3293590843677521
            ]
          ],
          "time_ms": 80975.0,
          "error": null
        },
        "EasyOCR": {
          "texts": [
            [
              "Onternationat",
              0.8750357965416655
            ],
            [
              "DAYTONA",
              0.6452011113017296
            ]
          ],
          "time_ms": 9706.6,
          "error": null
        },
        "docTR": {
          "texts": [
            [
              "9nternationa",
              0.575232982635498
            ],
            [
              "9Ba.",
              0.46652430295944214
            ],
            [
              "SPEEDWAY BEACH",
              0.4446480721235275
            ],
            [
              "DAYIONA",
              0.6258828639984131
            ]
          ],
          "time_ms": 1035.5,
          "error": null
        }
      }
    },
    {
      "image": "_DSC0036.jpg",
      "engines": {
        "PaddleOCR": {
          "texts": [
            [
              "A",
              0.3887571394443512
            ],
            [
              "RIDE INTO SPACE 35 CEN",
              0.9307317137718201
            ],
            [
              "POPULAR",
              0.9944610595703125
            ],
            [
              "DEC. 1958",
              0.9762102961540222
            ],
            [
              "MAGAZINE",
              0.9996179938316345
            ],
            [
              "MECHANICS",
              0.8674467206001282
            ],
            [
              "DECI",
              0.9987087845802307
            ],
            [
              "SAFETY",
              0.9827191233634949
            ],
            [
              "Aviation",
              0.9997153878211975
            ],
            [
              "Time",
              0.9978060126304626
            ],
            [
              "The Electri Drill",
              0.9556729793548584
            ],
            [
              "Atoric Sabmarine Tanter-Page 102",
              0.9170119762420654
            ],
            [
              "WHAT WE'RE DOING ABOUT",
              0.9944090247154236
            ],
            [
              "The Greatest Maric Wlusions of",
              0.88804692029953
            ],
            [
              "HOWCASE of TOOLS:",
              0.9727999567985535
            ],
            [
              "SAISES",
              0.4003278315067291
            ]
          ],
          "time_ms": 93180.0,
          "error": null
        },
        "EasyOCR": {
          "texts": [
            [
              "8",
              0.981004357147075
            ],
            [
              "2",
              0.41473077161910865
            ],
            [
              "4",
              0.9355168506311919
            ],
            [
              "4",
              0.9886907045381896
            ],
            [
              "3",
              0.9489204985051316
            ],
            [
              "1",
              0.4285878923210227
            ],
            [
              "1",
              0.47425533998279334
            ],
            [
              "DECF",
              0.3523269295692444
            ],
            [
              "1",
              0.5956650910015959
            ],
            [
              "Electri",
              0.6557382285089811
            ],
            [
              "1",
              0.3316636457441291
            ],
            [
              "1",
              0.8757278054015529
            ],
            [
              ":Illusions =",
              0.3070435807810965
            ],
            [
              "]",
              0.5647900715999299
            ],
            [
              "1",
              0.9165624204651976
            ],
            [
              "1",
              0.9650544844896025
            ],
            [
              "]",
              0.7785841713695305
            ],
            [
              "Buy F",
              0.5425213410008196
            ],
            [
              "]",
              0.5832185845466853
            ],
            [
              "1",
              0.7259009497636413
            ],
            [
              "ujisJhJ",
              0.3082413437788701
            ],
            [
              "so3oegc",
              0.3120334636632063
            ]
          ],
          "time_ms": 9949.6,
          "error": null
        },
        "docTR": {
          "texts": [
            [
              "A 6",
              0.3741493225097656
            ],
            [
              "A - - A",
              0.5394559539854527
            ],
            [
              "S",
              0.6465036869049072
            ]
          ],
          "time_ms": 1015.2,
          "error": null
        }
      }
    },
    {
      "image": "_DSC1047.jpg",
      "engines": {
        "PaddleOCR": {
          "texts": [
            [
              "HOME",
              0.9992164969444275
            ],
            [
              "GUEST",
              0.9989742040634155
            ],
            [
              "STRONG",
              0.8820944428443909
            ],
            [
              "STRONG",
              0.9875155091285706
            ]
          ],
          "time_ms": 68701.2,
          "error": null
        },
        "EasyOCR": {
          "texts": [],
          "time_ms": 8905.0,
          "error": null
        },
        "docTR": {
          "texts": [],
          "time_ms": 919.2,
          "error": null
        }
      }
    },
    {
      "image": "img017 copy.jpg",
      "engines": {
        "PaddleOCR": {
          "texts": [
            [
              "T",
              0.329424649477005
            ],
            [
              "nde",
              0.4133552610874176
            ]
          ],
          "time_ms": 61810.2,
          "error": null
        },
        "EasyOCR": {
          "texts": [
            [
              "Bakenlftshop",
              0.693118684456307
            ],
            [
              "Hesiess",
              0.5797510489373765
            ]
          ],
          "time_ms": 7567.9,
          "error": null
        },
        "docTR": {
          "texts": [
            [
              "-",
              0.836449921131134
            ],
            [
              "-",
              0.5170702934265137
            ],
            [
              "WONDER",
              0.8641085624694824
            ],
            [
              "HOSESS",
              0.3255753517150879
            ],
            [
              "$ Baken Pnswoy",
              0.4995709757010142
            ]
          ],
          "time_ms": 1010.2,
          "error": null
        }
      }
    },
    {
      "image": "testimage01.jpg",
      "engines": {
        "PaddleOCR": {
          "texts": [
            [
              "42",
              0.47714975476264954
            ],
            [
              "MTE",
              0.4437812268733978
            ],
            [
              "SAEARE",
              0.8066153526306152
            ],
            [
              "4.85",
              0.8375611305236816
            ],
            [
              "BOWL3.80",
              0.8657060861587524
            ],
            [
              "ESIOUSTE",
              0.5287199020385742
            ],
            [
              "TNESADNICH",
              0.6369574666023254
            ],
            [
              "3.75",
              0.7941625118255615
            ],
            [
              "CHILE CUP 280",
              0.8761947154998779
            ],
            [
              "1.50",
              0.9079663753509521
            ],
            [
              "EN",
              0.48068591952323914
            ],
            [
              "EONIOEEPEMER",
              0.793674647808075
            ],
            [
              "1.50",
              0.9251756072044373
            ],
            [
              "STEAK FES",
              0.7571884989738464
            ],
            [
              "HLLED CHETSE325",
              0.6971251368522644
            ],
            [
              "SANDWICHES",
              0.9160053133964539
            ],
            [
              "DACINO'S",
              0.806341826915741
            ],
            [
              "POTATO SAEAD",
              0.9325786232948303
            ],
            [
              "RILLED BAR E CHEESE 3.95",
              0.6556791067123413
            ],
            [
              "EN F CREESE SSAONICH",
              0.7158128619194031
            ],
            [
              "BREAD",
              0.967562198638916
            ],
            [
              "MAC SAEAD",
              0.8512830138206482
            ],
            [
              "ARFRADEON",
              0.7009583711624146
            ],
            [
              "HILLED TUNE E CHEESE 395",
              0.8113884329795837
            ],
            [
              "OUR FRESH",
              0.8058508038520813
            ],
            [
              "300 10F",
              0.6719101071357727
            ],
            [
              "MESTERE E SANIN",
              0.697597861289978
            ],
            [
              "HEEEDE CHICKEN",
              0.8821139931678772
            ],
            [
              "PRICAKES",
              0.7777321338653564
            ],
            [
              "HOREBADEBREAD",
              0.667622447013855
            ],
            [
              "FNEICH TOAST",
              0.6784144043922424
            ],
            [
              "ROASTEBEEE",
              0.7511379718780518
            ],
            [
              "EN",
              0.42473655939102173
            ],
            [
              "CHICKERPARE",
              0.87636798620224
            ],
            [
              "BICOIE O SISAGE",
              0.7495205402374268
            ],
            [
              "IS4",
              0.3142036497592926
            ],
            [
              "AVEDSTRAK",
              0.8350550532341003
            ],
            [
              "DIMEFRIES OF ASIRIONS",
              0.7047214508056641
            ],
            [
              "EE",
              0.32774078845977783
            ],
            [
              "EGUISE MFTI OR BAGEL",
              0.670423150062561
            ],
            [
              "CREAN OESE",
              0.6956359148025513
            ],
            [
              "PEAM T TER",
              0.8576589822769165
            ],
            [
              "WARNING: Persons ten",
              0.9825081825256348
            ],
            [
              "for redemption container",
              0.9730059504508972
            ],
            [
              "EP",
              0.9983644485473633
            ],
            [
              "which a deposit was nev",
              0.9757691025733948
            ],
            [
              "in this state may be sub",
              0.9569041132926941
            ],
            [
              "civil penalty of up to one",
              0.9162941575050354
            ],
            [
              "dollars per container or",
              0.9847357273101807
            ],
            [
              "twenty-five thousand do",
              0.9204654097557068
            ],
            [
              "EANO",
              0.3675389885902405
            ],
            [
              "each such tender of co",
              0.9980902075767517
            ],
            [
              "JHOSEVW",
              0.5600944757461548
            ]
          ],
          "time_ms": 71843.9,
          "error": null
        },
        "EasyOCR": {
          "texts": [
            [
              "2",
              0.8310767096060232
            ],
            [
              "tendenng",
              0.6853815482303839
            ],
            [
              "WARNING'",
              0.7164892679663476
            ],
            [
              "for reda",
              0.5293036787905144
            ],
            [
              "never",
              0.7293257945257348
            ],
            [
              "subiect",
              0.61326220279525
            ],
            [
              "one hundred",
              0.9987527346516192
            ],
            [
              "Denally 01",
              0.3794212924998624
            ],
            [
              "'container",
              0.71221544594103
            ],
            [
              "up to",
              0.6052442578562618
            ],
            [
              "icand dollars",
              0.6558305541122256
            ],
            [
              "aentyucre lender 0f containers",
              0.3601859516491702
            ],
            [
              "Persons",
              0.996039038087634
            ],
            [
              "Ilalners",
              0.6576377601819312
            ],
            [
              "'deposi",
              0.3535105114853332
            ]
          ],
          "time_ms": 9229.2,
          "error": null
        },
        "docTR": {
          "texts": [
            [
              "BO",
              0.6572934985160828
            ],
            [
              "CU 20",
              0.43163856863975525
            ],
            [
              "CIEE",
              0.461124449968338
            ],
            [
              "a",
              0.3376005291938782
            ],
            [
              "300",
              0.8638231158256531
            ],
            [
              "-",
              0.8242631554603577
            ],
            [
              "I",
              0.8217997550964355
            ],
            [
              "5",
              0.6548449993133545
            ],
            [
              ":",
              0.6183139085769653
            ],
            [
              "E",
              0.44339320063591003
            ],
            [
              ":",
              0.6824740171432495
            ],
            [
              "AFT9",
              0.3427216708660126
            ],
            [
              "HEEE",
              0.5749177932739258
            ],
            [
              "NNISD",
              0.5679875016212463
            ],
            [
              "MN",
              0.33235466480255127
            ]
          ],
          "time_ms": 2398.5,
          "error": null
        }
      }
    },
    {
      "image": "testimage02.jpg",
      "engines": {
        "PaddleOCR": {
          "texts": [
            [
              "NAAMN",
              0.5130950212478638
            ],
            [
              "WWK",
              0.3689310550689697
            ],
            [
              "MMMMI",
              0.5673943758010864
            ],
            [
              "WHWROWHN",
              0.3510006368160248
            ],
            [
              "MMMMMI",
              0.6156726479530334
            ],
            [
              "MMMN",
              0.3772570788860321
            ],
            [
              "LupT",
              0.4125291407108307
            ],
            [
              "T",
              0.5671429634094238
            ],
            [
              "601/2/9040 M.3011N",
              0.6180276274681091
            ]
          ],
          "time_ms": 86637.1,
          "error": null
        },
        "EasyOCR": {
          "texts": [],
          "time_ms": 9313.9,
          "error": null
        },
        "docTR": {
          "texts": [],
          "time_ms": 1079.4,
          "error": null
        }
      }
    },
    {
      "image": "testimage03.jpg",
      "engines": {
        "PaddleOCR": {
          "texts": [
            [
              "+",
              0.4685899317264557
            ]
          ],
          "time_ms": 72329.0,
          "error": null
        },
        "EasyOCR": {
          "texts": [],
          "time_ms": 10363.0,
          "error": null
        },
        "docTR": {
          "texts": [],
          "time_ms": 1428.2,
          "error": null
        }
      }
    },
    {
      "image": "testimage04.jpg",
      "engines": {
        "PaddleOCR": {
          "texts": [
            [
              "034",
              0.509784996509552
            ],
            [
              "S",
              0.42689234018325806
            ]
          ],
          "time_ms": 78306.3,
          "error": null
        },
        "EasyOCR": {
          "texts": [],
          "time_ms": 9132.4,
          "error": null
        },
        "docTR": {
          "texts": [
            [
              "1",
              0.3529025614261627
            ],
            [
              "GAF ARE dF",
              0.44161564111709595
            ],
            [
              "-",
              0.5032072067260742
            ],
            [
              "-",
              0.6407181024551392
            ],
            [
              "-",
              0.42275768518447876
            ]
          ],
          "time_ms": 1168.4,
          "error": null
        }
      }
    },
    {
      "image": "testimage05.jpg",
      "engines": {
        "PaddleOCR": {
          "texts": [
            [
              "P e NE",
              0.40840521454811096
            ],
            [
              "HONT",
              0.5611383318901062
            ],
            [
              "BOO AA AAE",
              0.4425048232078552
            ],
            [
              "L2ZX2L",
              0.37705716490745544
            ],
            [
              "88009088",
              0.52202969789505
            ],
            [
              "2220",
              0.6845306754112244
            ],
            [
              "003000",
              0.6517677307128906
            ],
            [
              "SanD WnE t",
              0.3876323103904724
            ],
            [
              "TEXY",
              0.47366636991500854
            ],
            [
              "Handared",
              0.7761473655700684
            ],
            [
              "MND A.C00",
              0.4007105827331543
            ],
            [
              "HESHEHS",
              0.47343897819519043
            ],
            [
              "HHEHSES",
              0.4516175091266632
            ],
            [
              "SSSS OOE",
              0.3934151828289032
            ],
            [
              "Z227",
              0.5224955677986145
            ],
            [
              "0",
              0.484576016664505
            ],
            [
              "0000",
              0.5243325233459473
            ],
            [
              "av",
              0.3468364477157593
            ],
            [
              "ASE LIGHTING",
              0.9629425406455994
            ],
            [
              "MULII",
              0.8270570635795593
            ]
          ],
          "time_ms": 72201.1,
          "error": null
        },
        "EasyOCR": {
          "texts": [
            [
              "607",
              0.7619933033782923
            ],
            [
              "535328",
              0.8261915148689649
            ],
            [
              "DSE LIGHTING",
              0.4661382300992765
            ],
            [
              "LzzztdXJoL",
              0.3939631296144865
            ]
          ],
          "time_ms": 9440.3,
          "error": null
        },
        "docTR": {
          "texts": [
            [
              "if",
              0.7498157024383545
            ]
          ],
          "time_ms": 1131.0,
          "error": null
        }
      }
    },
    {
      "image": "testimage06.jpg",
      "engines": {
        "PaddleOCR": {
          "texts": [
            [
              "4",
              0.4585561156272888
            ]
          ],
          "time_ms": 67647.7,
          "error": null
        },
        "EasyOCR": {
          "texts": [],
          "time_ms": 9830.8,
          "error": null
        },
        "docTR": {
          "texts": [],
          "time_ms": 877.8,
          "error": null
        }
      }
    },
    {
      "image": "testimage07.jpg",
      "engines": {
        "PaddleOCR": {
          "texts": [
            [
              "7",
              0.5430642366409302
            ]
          ],
          "time_ms": 72477.4,
          "error": null
        },
        "EasyOCR": {
          "texts": [],
          "time_ms": 12828.1,
          "error": null
        },
        "docTR": {
          "texts": [
            [
              "a",
              0.47210797667503357
            ],
            [
              "E",
              0.48305314779281616
            ]
          ],
          "time_ms": 1033.9,
          "error": null
        }
      }
    },
    {
      "image": "testimage08.jpg",
      "engines": {
        "PaddleOCR": {
          "texts": [
            [
              "D",
              0.4247644245624542
            ],
            [
              "I",
              0.32395756244659424
            ],
            [
              "5",
              0.3056793212890625
            ],
            [
              "72",
              0.5484748482704163
            ],
            [
              "RR",
              0.49070990085601807
            ],
            [
              "3-",
              0.63447105884552
            ],
            [
              "RKSE",
              0.3775983154773712
            ],
            [
              "y",
              0.4662233293056488
            ],
            [
              "7",
              0.39323148131370544
            ],
            [
              "TU",
              0.5008638501167297
            ],
            [
              "7937",
              0.6607887744903564
            ],
            [
              "4",
              0.7717638611793518
            ],
            [
              "TH",
              0.5714516043663025
            ],
            [
              "TC",
              0.4756864309310913
            ],
            [
              "EKMZWRE",
              0.353182315826416
            ],
            [
              "ST",
              0.49002575874328613
            ],
            [
              "TAK52",
              0.3382887542247772
            ]
          ],
          "time_ms": 76610.5,
          "error": null
        },
        "EasyOCR": {
          "texts": [],
          "time_ms": 8691.9,
          "error": null
        },
        "docTR": {
          "texts": [
            [
              "-",
              0.8273334503173828
            ]
          ],
          "time_ms": 981.2,
          "error": null
        }
      }
    },
    {
      "image": "testimage09.jpg",
      "engines": {
        "PaddleOCR": {
          "texts": [],
          "time_ms": 68623.5,
          "error": null
        },
        "EasyOCR": {
          "texts": [],
          "time_ms": 7978.6,
          "error": null
        },
        "docTR": {
          "texts": [
            [
              "a 1",
              0.6506214737892151
            ],
            [
              "4",
              0.412422239780426
            ],
            [
              "N 4",
              0.5776385366916656
            ],
            [
              "\u00e0 3",
              0.3077341765165329
            ],
            [
              "1",
              0.39175963401794434
            ],
            [
              "- -",
              0.652953028678894
            ],
            [
              "E",
              0.33741000294685364
            ]
          ],
          "time_ms": 1259.7,
          "error": null
        }
      }
    },
    {
      "image": "testimage10.jpg",
      "engines": {
        "PaddleOCR": {
          "texts": [
            [
              "mmm",
              0.6082866787910461
            ],
            [
              "BA",
              0.39931127429008484
            ]
          ],
          "time_ms": 106831.9,
          "error": null
        },
        "EasyOCR": {
          "texts": [],
          "time_ms": 8599.1,
          "error": null
        },
        "docTR": {
          "texts": [],
          "time_ms": 1141.2,
          "error": null
        }
      }
    },
    {
      "image": "the-coliseum-interior-roller-blade-wheels.jpg",
      "engines": {
        "PaddleOCR": {
          "texts": [
            [
              "aS",
              0.40191638469696045
            ],
            [
              "BAA",
              0.47767171263694763
            ],
            [
              "SEI",
              0.972428023815155
            ],
            [
              "0",
              0.7704113125801086
            ],
            [
              "K",
              0.9996246099472046
            ],
            [
              "T",
              0.32640528678894043
            ],
            [
              "1203",
              0.9990692138671875
            ]
          ],
          "time_ms": 10471.9,
          "error": null
        },
        "EasyOCR": {
          "texts": [
            [
              "1202",
              0.9914236068725586
            ],
            [
              "8",
              0.6030410033378395
            ],
            [
              "SKATES",
              0.9981640969198107
            ],
            [
              "in-LINE",
              0.6641844008880812
            ],
            [
              "824",
              0.7383726146474202
            ],
            [
              "8",
              0.9783152319563584
            ]
          ],
          "time_ms": 3270.0,
          "error": null
        },
        "docTR": {
          "texts": [
            [
              "KINE 82A SKATES",
              0.8087092638015747
            ],
            [
              "o e",
              0.526836633682251
            ],
            [
              "- 8",
              0.5976100116968155
            ]
          ],
          "time_ms": 827.6,
          "error": null
        }
      }
    },
    {
      "image": "the-coliseum-interior-sign.jpg",
      "engines": {
        "PaddleOCR": {
          "texts": [
            [
              "RINK",
              0.9997227787971497
            ],
            [
              "POLICY",
              0.9994792938232422
            ],
            [
              "NO",
              0.9881793856620789
            ],
            [
              "CAN",
              0.9997981190681458
            ],
            [
              "BE",
              0.9997074604034424
            ],
            [
              "GUARANTEED",
              0.9998067617416382
            ],
            [
              "THAT",
              0.99981689453125
            ],
            [
              "THEY",
              0.9996142983436584
            ],
            [
              "WILL",
              0.9998231530189514
            ],
            [
              "PERSON",
              0.9805744290351868
            ],
            [
              "THEY",
              0.999753475189209
            ],
            [
              "PUT",
              0.9997463226318359
            ],
            [
              "ON",
              0.9991796016693115
            ],
            [
              "A",
              0.9900315999984741
            ],
            [
              "PAIR",
              0.999847948551178
            ],
            [
              "OF",
              0.9958593845367432
            ],
            [
              "ROLLER",
              0.9993500113487244
            ],
            [
              "NOT",
              0.9995010495185852
            ],
            [
              "FALL",
              0.999873161315918
            ],
            [
              "IF",
              0.9988746643066406
            ],
            [
              "SKATE",
              0.9992432594299316
            ],
            [
              "AT",
              0.9998753070831299
            ],
            [
              "YOUR",
              0.9995684623718262
            ],
            [
              "OWN",
              0.9992350935935974
            ],
            [
              "RISK-WE",
              0.9993192553520203
            ],
            [
              "SKATES.",
              0.998539388179779
            ],
            [
              "YOU",
              0.9991912841796875
            ],
            [
              "FOR",
              0.9990232586860657
            ],
            [
              "ACCIDENTS",
              0.9996737241744995
            ],
            [
              "TO",
              0.9959859848022461
            ],
            [
              "ASSUME",
              0.9996557235717773
            ],
            [
              "NO",
              0.9941315650939941
            ],
            [
              "LIABILITY",
              0.9996457695960999
            ],
            [
              "SKATERS.",
              0.9988242387771606
            ],
            [
              "PLEASE",
              0.999809741973877
            ],
            [
              "SKATE",
              0.9996544122695923
            ],
            [
              "CAREFULLY",
              0.9997826814651489
            ],
            [
              "THE",
              0.9998257160186768
            ],
            [
              "MANAGEMENT.",
              0.9967828989028931
            ]
          ],
          "time_ms": 14688.3,
          "error": null
        },
        "EasyOCR": {
          "texts": [
            [
              "Rink",
              0.9205992817878723
            ],
            [
              "PoLicy",
              0.39669227398479145
            ],
            [
              "No PERSON CAN BE GUARANTEED THAT  THEY WILL",
              0.32925952296124167
            ],
            [
              "NOT FALL IF THEY",
              0.5403297457451479
            ],
            [
              "Put On A PAiR OF",
              0.5241672859721421
            ],
            [
              "ROLLER",
              0.7982271576967633
            ],
            [
              "SKATES",
              0.825814952392931
            ],
            [
              "You SKATE AT YOUR OwN Risk-WE",
              0.44624143453512144
            ],
            [
              "ASSUME NO LIABILITY",
              0.737005183566771
            ],
            [
              "FoR ACCIDENTS To",
              0.644490327189095
            ],
            [
              "SKATERS.",
              0.7891614421916071
            ],
            [
              "SKATE CAREFULLY PLEASE",
              0.9492599455322608
            ],
            [
              "THE MANAGEMENT;",
              0.8599875311786528
            ]
          ],
          "time_ms": 3135.4,
          "error": null
        },
        "docTR": {
          "texts": [
            [
              "RINK",
              0.9873282313346863
            ],
            [
              "POLICY",
              0.997433602809906
            ],
            [
              "NO PERSON CAN BE GUARANTEED THAT THEY WILL",
              0.9973524436354637
            ],
            [
              "a",
              0.44783633947372437
            ],
            [
              "NOT FALL IF THEY PUT ON A PAIR OF ROLLER",
              0.9898225963115692
            ],
            [
              "SKATES. YOU'SKATE AT YOUR OWN RISK-WE",
              0.9775673449039459
            ],
            [
              "ASSUME NO LIABILITY FOR ACCIDENTS TO",
              0.9328133662541708
            ],
            [
              "SKATERS.",
              0.9554492235183716
            ],
            [
              "SKATE CAREFULLY PLEASE THE MANAGEMENT. -",
              0.9059110234181086
            ]
          ],
          "time_ms": 2404.8,
          "error": null
        }
      }
    }
  ]
}